<?xml version="1.0" encoding="UTF-8"?>
<list xmlns:xsi="http://www.w3.org/2001/XMLSchema-instance" xsi:noNamespaceSchemaLocation="../../../xsd/skills.xsd">
	<skill id="5900" levels="1" name="Burst of Oblivion">
		<set name="abnormalLvl" val="8" />
		<set name="abnormalTime" val="10" />
		<set name="abnormalType" val="oblivion" />
		<set name="abnormalVisualEffect" val="DOT_POISON" />
		<set name="activateRate" val="90" />
		<set name="affectLimit" val="5-15" />
		<set name="basicProperty" val="MEN" />
		<set name="effectPoint" val="-100" />
		<set name="fanRange" val="0,0,150,90" />
		<set name="hitTime" val="2000" />
		<set name="icon" val="icon.skill1481" />
		<set name="isDebuff" val="true" />
		<set name="offensive" val="true" />
		<set name="isMagic" val="1" /> <!-- Magic Skill -->
		<set name="lvlBonusRate" val="1" />
		<set name="magicLvl" val="85" />
		<set name="operateType" val="A2" />
		<set name="rideState" val="NONE;STRIDER;WYVERN;WOLF" />
		<set name="targetType" val="FRONT_AREA" />
		<set name="trait" val="DERANGEMENT" />
		<for>
			<effect name="TriggerSkillByAttack" abnormalTime="10" val="0" abnormalLvl="8" abnormalType="oblivion">
				<param attackerType="L2Character" minAttackerLevel="1" maxAttackerLevel="99" />
				<param isCritical="false" />
				<param minDamage="1" chance="90" />
				<param skillId="5902" skillLevel="1" /> <!-- NPC Trigger Target Cancel -->
				<param targetType="SELF" />
				<param allowWeapons="ALL" />
			</effect>
		</for>
	</skill>
	<skill id="5901" levels="2" name="Mist of Oblivion">
		<table name="#hitTime"> 2000 22940 </table>
		<set name="abnormalLvl" val="8" />
		<set name="abnormalTime" val="10" />
		<set name="abnormalType" val="oblivion" />
		<set name="abnormalVisualEffect" val="dot_poison" />
		<set name="activateRate" val="90" />
		<set name="affectLimit" val="10-10" />
		<set name="basicProperty" val="MEN" />
		<set name="effectPoint" val="-100" />
		<set name="hitTime" val="#hitTime" />
		<set name="icon" val="icon.skill1481" />
		<set name="isDebuff" val="true" />
		<set name="offensive" val="true" />
		<set name="isMagic" val="1" /> <!-- Magic Skill -->
		<set name="lvlBonusRate" val="1" />
		<set name="magicLvl" val="85" />
		<set name="operateType" val="A2" />
		<set name="rideState" val="NONE;STRIDER;WYVERN;WOLF" />
		<set name="targetType" val="NONE" />
		<set name="trait" val="DERANGEMENT" />
		<for>
			<effect name="TriggerSkillByAttack" abnormalTime="10" val="0" abnormalLvl="8" abnormalType="oblivion">
				<param attackerType="L2Character" minAttackerLevel="1" maxAttackerLevel="99" />
				<param isCritical="false" />
				<param minDamage="1" chance="90" />
				<param skillId="5902" skillLevel="1" /> <!-- NPC Trigger Target Cancel -->
				<param targetType="SELF" />
				<param allowWeapons="ALL" />
			</effect>
		</for>
	</skill>
	<skill id="5902" levels="1" name="NPC Trigger Target Cancel">
		<!-- Confirmed CT2.5 -->
		<!-- Ekimus Skills -->
		<set name="isTriggeredSkill" val="true" />
		<set name="magicLvl" val="85" />
		<set name="operateType" val="A1" />
		<set name="skillType" val="BUFF" />
		<set name="targetType" val="SELF" />
		<for>
			<effect name="RemoveTarget" noicon="1" val="0" />
		</for>
	</skill>
	<skill id="5903" levels="1" name="Burst of Misplace">
		<set name="abnormalLvl" val="1" />
		<set name="abnormalTime" val="3" />
		<set name="abnormalType" val="disarm" />
		<set name="affectLimit" val="5-15" />
		<set name="castRange" val="600" />
		<set name="effectRange" val="1100" />
		<set name="fanRange" val="0,0,600,90" />
		<set name="hitTime" val="2000" />
		<set name="isDebuff" val="true" />
		<set name="isMagic" val="1" /> <!-- Magic Skill -->
		<set name="lvlBonusRate" val="1" />
		<set name="magicLvl" val="83" />
		<set name="mpConsume" val="74" />
		<set name="operateType" val="A2" />
		<set name="power" val="70" /> <!-- Base Land Rate -->
		<set name="offensive" val="true" />
		<set name="basicProperty" val="STR" />
		<set name="skillType" val="DISARM" />
		<set name="soulMaxConsumeCount" val="1" />
		<set name="targetType" val="FRONT_AREA" />
		<for>
			<effect name="Disarm" abnormalTime="5" val="0" abnormalVisualEffect="bleed" abnormalLvl="1" abnormalType="disarm" />
		</for>
	</skill>
	<skill id="5904" levels="3" name="Mist of Souleater">
		<table name="#hitTime"> 2000 22940 22940 </table>
		<table name="#magicLvl"> 77 81 83 </table>
		<table name="#mpConsume"> 146 150 153 </table>
		<table name="#mpInitialConsume"> 37 38 39 </table>
		<table name="#power"> 112 117 120 </table>
		<set name="absorbPart" val="0.8" />
		<set name="affectLimit" val="10-10" />
		<set name="affectRange" val="300" />
		<set name="castRange" val="900" />
		<set name="effectRange" val="1400" />
		<set name="hitTime" val="#hitTime" />
		<set name="isMagic" val="1" /> <!-- Magic Skill -->
		<set name="magicLvl" val="#magicLvl" />
		<set name="mpConsume" val="#mpConsume" />
		<set name="mpInitialConsume" val="#mpInitialConsume" />
		<set name="offensive" val="true" />
		<set name="operateType" val="A1" />
		<set name="power" val="#power" />
		<set name="skillType" val="DRAIN" />
		<set name="targetType" val="AURA" />
	</skill>
	<skill id="5905" levels="1" name="Confusing Nuph">
		<set name="abnormalLvl" val="1" />
		<set name="abnormalTime" val="3" />
		<set name="abnormalType" val="silence_all" />
		<set name="affectLimit" val="10-10" />
		<set name="hitTime" val="2000" />
		<set name="isMagic" val="1" /> <!-- Magic Skill -->
		<set name="lvlBonusRate" val="1" />
		<set name="operateType" val="A2" />
		<set name="basicProperty" val="MEN" />
		<set name="skillType" val="NOTDONE" />
		<set name="targetType" val="NONE" />
		<set name="trait" val="DERANGEMENT" />
	</skill>
	<skill id="5906" levels="1" name="Ritual of Revive">
		<set name="hitTime" val="3000" />
		<set name="isMagic" val="1" /> <!-- Magic Skill -->
		<set name="operateType" val="A1" />
		<set name="skillType" val="NOTDONE" />
		<set name="targetType" val="NONE" />
	</skill>
	<skill id="5907" levels="2" name="Ritual of Entombment">
		<table name="#hitTime"> 3000 34400 </table>
		<set name="abnormalLvl" val="1" />
		<set name="abnormalTime" val="10" />
		<set name="abnormalType" val="root_magically" />
		<set name="affectLimit" val="10-10" />
		<set name="hitTime" val="#hitTime" />
		<set name="isMagic" val="1" /> <!-- Magic Skill -->
		<set name="lvlBonusRate" val="1" />
		<set name="operateType" val="A2" />
		<set name="basicProperty" val="MEN" />
		<set name="skillType" val="NOTDONE" />
		<set name="targetType" val="NONE" />
	</skill>
	<skill id="5908" levels="2" name="Ritual of Entombment">
		<table name="#hitTime"> 3000 34400 </table>
		<set name="abnormalLvl" val="1" />
		<set name="abnormalTime" val="10" />
		<set name="abnormalType" val="root_magically" />
		<set name="affectLimit" val="10-10" />
		<set name="hitTime" val="#hitTime" />
		<set name="isMagic" val="1" /> <!-- Magic Skill -->
		<set name="lvlBonusRate" val="1" />
		<set name="operateType" val="A2" />
		<set name="basicProperty" val="MEN" />
		<set name="skillType" val="NOTDONE" />
		<set name="targetType" val="NONE" />
	</skill>
	<skill id="5909" levels="1" name="Stronghold Attack">
		<set name="castRange" val="40" />
		<set name="effectRange" val="400" />
		<set name="hitTime" val="1000" />
		<set name="isMagic" val="1" /> <!-- Magic Skill -->
		<set name="offensive" val="true" />
		<set name="operateType" val="A1" />
		<set name="power" val="3000" />
		<set name="reuseDelay" val="1000" />
		<set name="skillType" val="PDAM" /> <!-- FIXME: value unconfirmed -->
		<set name="targetType" val="ONE" />
	</skill>
	<skill id="5910" levels="1" name="Stronghold Attack">
		<set name="castRange" val="300" />
		<set name="effectRange" val="500" />
		<set name="hitTime" val="1000" />
		<set name="isMagic" val="1" /> <!-- Magic Skill -->
		<set name="offensive" val="true" />
		<set name="operateType" val="A1" />
		<set name="power" val="5000" />
		<set name="reuseDelay" val="1000" />
		<set name="skillType" val="PDAM" /> <!-- FIXME: value unconfirmed -->
		<set name="targetType" val="ONE" />
	</skill>
	<skill id="5911" levels="1" name="Pestilence Cleanse">
		<set name="operateType" val="P" />
		<set name="skillType" val="NOTDONE" />
		<set name="targetType" val="NONE" />
	</skill>
	<skill id="5912" levels="1" name="Pestilence Cleanse">
		<set name="abnormalLvl" val="1" />
		<set name="abnormalTime" val="10" />
		<set name="abnormalType" val="multi_debuff_d" />
		<set name="isMagic" val="1" /> <!-- Magic Skill -->
		<set name="lvlBonusRate" val="1" />
		<set name="operateType" val="A2" />
		<set name="basicProperty" val="MEN" />
		<set name="skillType" val="NOTDONE" />
		<set name="targetType" val="NONE" />
		<set name="trait" val="DERANGEMENT" />
	</skill>
	<skill id="5913" levels="1" name="Putrefection Cleanse">
		<set name="magicLvl" val="83" />
		<set name="operateType" val="P" />
		<set name="targetType" val="SELF" />
		<for>
			<effect name="TriggerSkillByAttack" nocicon="1" val="0">
				<param attackerType="L2Character" minAttackerLevel="1" maxAttackerLevel="100" />
				<param isCritical="false" />
				<param minDamage="1" chance="100" />
				<param skillId="5914" skillLevel="1" /> <!-- Putrefaction Cleanse -->
				<param targetType="ONE" />
				<param allowWeapons="ALL" />
			</effect>
		</for>
	</skill>
	<skill id="5914" levels="1" name="Putrefaction Cleanse">
		<set name="abnormalLvl" val="1" />
		<set name="abnormalTime" val="10" />
		<set name="abnormalType" val="multi_debuff_e" />
		<set name="isMagic" val="1" /> <!-- Magic Skill -->
		<set name="lvlBonusRate" val="1" />
		<set name="operateType" val="A2" />
		<set name="basicProperty" val="MEN" />
		<set name="skillType" val="NOTDONE" />
		<set name="targetType" val="NONE" />
		<set name="trait" val="DERANGEMENT" />
	</skill>
	<skill id="5915" levels="9" name="Mummifying Aura">
		<table name="#abnormalLvls"> 1 2 3 4 5 6 7 8 9 </table>
		<set name="abnormalLvl" val="#abnormalLvls" />
		<set name="abnormalTime" val="3600" />
		<set name="abnormalType" val="pd_up" />
		<set name="isMagic" val="1" /> <!-- Magic Skill -->
		<set name="operateType" val="A2" />
		<set name="skillType" val="NOTDONE" />
		<set name="targetType" val="NONE" />
	</skill>
	<skill id="5916" levels="9" name="Cruising Aura">
		<table name="#abnormalLvls"> 1 2 3 4 5 6 7 8 9 </table>
		<set name="abnormalLvl" val="#abnormalLvls" />
		<set name="abnormalTime" val="3600" />
		<set name="abnormalType" val="pa_up" />
		<set name="isMagic" val="1" /> <!-- Magic Skill -->
		<set name="operateType" val="A2" />
		<set name="skillType" val="NOTDONE" />
		<set name="targetType" val="NONE" />
	</skill>
	<skill id="5917" levels="9" name="Shrouding Aura">
		<table name="#abnormalLvls"> 1 2 3 4 5 6 7 8 9 </table>
		<set name="abnormalLvl" val="#abnormalLvls" />
		<set name="abnormalTime" val="3600" />
		<set name="abnormalType" val="avoid_skill" />
		<set name="isMagic" val="1" /> <!-- Magic Skill -->
		<set name="operateType" val="A2" />
		<set name="skillType" val="NOTDONE" />
		<set name="targetType" val="NONE" />
	</skill>
	<skill id="5918" levels="10" name="Physical Root Weakness">
		<set name="operateType" val="P" />
		<set name="skillType" val="NOTDONE" />
		<set name="targetType" val="NONE" />
	</skill>
	<skill id="5919" levels="1" name="Obey">
		<!-- Confirmed CT2.5 -->
		<!-- Ekimus Skills -->
		<set name="abnormalLvl" val="1" />
		<set name="abnormalTime" val="300" />
		<set name="abnormalType" val="block_resurrection" />
		<set name="castRange" val="300" />
		<set name="effectRange" val="600" />
		<set name="hitTime" val="12610" />
		<set name="isDebuff" val="true" />
		<set name="isMagic" val="1" /> <!-- Magic Skill -->
		<set name="mpConsume" val="60" />
		<set name="mpInitialConsume" val="15" />
		<set name="operateType" val="A2" />
		<set name="power" val="-1" /> <!-- Land Always -->
		<set name="offensive" val="true" />
		<set name="skillType" val="DEBUFF" />
		<set name="stayAfterDeath" val="true" />
		<set name="targetType" val="ONE" />
		<for>
			<effect name="BlockResurrection" abnormalTime="300" val="0" abnormalLvl="1" abnormalType="block_resurrection" />
		</for>
	</skill>
	<skill id="5920" levels="1" name="Tentacle of Agony">
		<!-- Confirmed CT2.5 -->
		<!-- Ekimus Skills -->
		<set name="affectRange" val="300" />
		<set name="coolTime" val="2000" />
		<set name="element" val="3" /> <!-- Earth -->
		<set name="elementPower" val="20" />
		<set name="hitTime" val="91740" />
		<set name="isMagic" val="1" /> <!-- Magic Skill -->
		<set name="magicLvl" val="85" />
		<set name="mpConsume" val="239" />
		<set name="mpInitialConsume" val="60" />
		<set name="offensive" val="true" />
		<set name="operateType" val="A1" />
		<set name="power" val="150" />
		<set name="skillType" val="MDAM" />
		<set name="targetType" val="AURA" />
	</skill>
	<skill id="5921" levels="1" name="Inhale">
		<!-- Confirmed CT2.5 -->
		<!-- Ekimus Skills -->
		<set name="abnormalLvl" val="1" />
		<set name="abnormalTime" val="10" />
		<set name="abnormalType" val="multi_debuff_f" />
		<set name="absorbPart" val="0.8" /> <!-- absorbs 80% of damage -->
		<set name="affectLimit" val="5-15" />
		<set name="affectRange" val="600" />
		<set name="castRange" val="600" />
		<set name="effectRange" val="1100" />
		<set name="fanRange" val="0,0,600,90" />
		<set name="hitTime" val="26950" />
		<set name="isDebuff" val="true" />
		<set name="isMagic" val="1" /> <!-- Magic Skill -->
		<set name="lvlBonusRate" val="1" />
		<set name="magicLvl" val="85" />
		<set name="mpConsume" val="179" />
		<set name="mpInitialConsume" val="45" />
		<set name="offensive" val="true" />
		<set name="operateType" val="A2" />
		<set name="power" val="121" />
		<set name="basicProperty" val="MEN" />
		<set name="skillType" val="DRAIN" />
		<set name="targetType" val="FRONT_AREA" />
		<for>
			<effect name="Debuff" abnormalTime="10" val="0" abnormalVisualEffect="bleed" effectPower="80" abnormalLvl="1" abnormalType="multi_debuff_f">
				<mul stat="pAtk" val="0.9" />
				<mul stat="pAtkSpd" val="0.95" />
				<mul stat="mAtk" val="0.95" />
				<sub stat="accCombat" val="3" />
				<basemul stat="critRate" val="-0.1" />
				<mul stat="critDmg" val="0.9" />
			</effect>
		</for>
	</skill>
	<skill id="5922" levels="1" name="Exhale">
		<!-- Confirmed CT2.5 -->
		<!-- Ekimus Skills -->
		<set name="abnormalLvl" val="1" />
		<set name="abnormalTime" val="10" />
		<set name="abnormalType" val="multi_debuff_g" />
		<set name="affectLimit" val="5-15" />
		<set name="affectRange" val="300" />
		<set name="castRange" val="600" />
		<set name="effectRange" val="1100" />
		<set name="hitTime" val="22700" />
		<set name="isMagic" val="1" /> <!-- Magic Skill -->
		<set name="lvlBonusRate" val="1" />
		<set name="magicLvl" val="85" />
		<set name="mpConsume" val="179" />
		<set name="mpInitialConsume" val="45" />
		<set name="offensive" val="true" />
		<set name="operateType" val="A2" />
		<set name="power" val="121" />
		<set name="basicProperty" val="MEN" />
		<set name="skillType" val="MDAM" />
		<set name="targetType" val="AREA" />
		<for>
			<effect name="Debuff" abnormalTime="10" val="0" abnormalVisualEffect="bleed" effectPower="80" abnormalLvl="1" abnormalType="multi_debuff_g">
				<sub stat="rEvas" val="3" />
				<mul stat="pDef" val="0.5" />
				<mul stat="mDef" val="0.5" />
				<mul stat="runSpd" val="0.5" />
			</effect>
		</for>
	</skill>
	<skill id="5923" levels="1" name="Soul Retain">
		<!-- Confirmed CT2.5 -->
		<set name="abnormalLvl" val="1" />
		<set name="abnormalTime" val="10800" />
		<set name="abnormalType" val="ma_up" />
		<set name="hitTime" val="1000" />
		<set name="isMagic" val="1" /> <!-- Magic Skill -->
		<set name="operateType" val="A2" />
		<set name="reuseDelay" val="1000" />
		<set name="skillType" val="BUFF" />
		<set name="targetType" val="SELF" />
		<for>
			<effect name="Buff" abnormalTime="10800" val="0" abnormalLvl="1" abnormalType="ma_up" >
				<mul stat="pDef" val="0.95" />
				<mul stat="mDef" val="0.95" />
				<mul stat="regHp" val="0.95" />
				<mul stat="mAtk" val="1.03" />
			</effect>
		</for>
	</skill>
	<skill id="5924" levels="1" name="Devour Soul">
		<set name="hitTime" val="5000" />
		<set name="isMagic" val="2" /> <!-- Static Skill -->
		<set name="operateType" val="A1" />
		<set name="skillType" val="NOTDONE" />
		<set name="targetType" val="NONE" />
	</skill>
	<skill id="5925" levels="1" name="Goring Charge">
		<set name="hitTime" val="800" />
		<set name="operateType" val="DA1" />
		<set name="skillType" val="NOTDONE" />
		<set name="targetType" val="NONE" />
		<cond msgId="113" addName="1">
			<target mindistance="200" />
		</cond>
	</skill>
	<skill id="5926" levels="1" name="Breath Corruption">
		<set name="affectLimit" val="5-15" />
		<set name="fanRange" val="0,0,300,90" />
		<set name="hitTime" val="2000" />
		<set name="isMagic" val="2" /> <!-- Static Skill -->
		<set name="operateType" val="A1" />
		<set name="skillType" val="NOTDONE" />
		<set name="targetType" val="FRONT_AREA" />
	</skill>
	<skill id="5927" levels="4" name="Immortal Frenzy">
		<table name="#abnormalLvls"> 1 2 3 4 </table>
		<set name="abnormalLvl" val="#abnormalLvls" />
		<set name="abnormalTime" val="3600" />
		<set name="abnormalType" val="pa_up" />
		<set name="operateType" val="A2" />
		<set name="skillType" val="NOTDONE" />
		<set name="targetType" val="NONE" />
	</skill>
	<skill id="5928" levels="4" name="Immortal Resilience">
		<table name="#abnormalLvls"> 1 2 3 4 </table>
		<set name="abnormalLvl" val="#abnormalLvls" />
		<set name="abnormalTime" val="3600" />
		<set name="abnormalType" val="pd_up" />
		<set name="operateType" val="A2" />
		<set name="skillType" val="NOTDONE" />
		<set name="targetType" val="NONE" />
	</skill>
	<skill id="5929" levels="1" name="Pairing of the Lost">
		<set name="abnormalLvl" val="1" />
		<set name="abnormalTime" val="3600" />
		<set name="abnormalType" val="counter_skill" />
		<set name="operateType" val="A2" />
		<set name="skillType" val="NOTDONE" />
		<set name="targetType" val="NONE" />
	</skill>
	<skill id="5930" levels="1" name="Shielding of the Lost">
		<set name="abnormalLvl" val="1" />
		<set name="abnormalTime" val="3600" />
		<set name="abnormalType" val="pd_up_bow" />
		<set name="operateType" val="A2" />
		<set name="skillType" val="NOTDONE" />
		<set name="targetType" val="NONE" />
	</skill>
	<skill id="5931" levels="1" name="Ultimate Shield">
		<!-- Confirmed CT2.5 -->
		<!-- Ekimus Skills -->
		<set name="magicLvl" val="85" />
		<set name="mpConsume" val="1" />
		<set name="operateType" val="T" />
		<set name="skillType" val="CONT" />
		<set name="targetType" val="SELF" />
		<for>
			<effect name="Invincible" abnormalTime="-1" val="0" />
		</for>
	</skill>
	<skill id="5932" levels="1" name="Dark Blade">
		<!-- Confirmed CT2.5 -->
		<!-- Ekimus Skills -->
		<set name="affectLimit" val="5-15" />
		<set name="affectRange" val="300" />
		<set name="castRange" val="900" />
		<set name="effectRange" val="1500" />
		<set name="element" val="5" /> <!-- Dark -->
		<set name="elementPower" val="180" />
		<set name="fanRange" val="0,0,300,160" />
		<set name="hitTime" val="1500" />
		<set name="magicLvl" val="85" />
		<set name="mpConsume" val="1" />
		<set name="offensive" val="true" />
		<set name="operateType" val="A1" />
		<set name="power" val="9279" />
		<set name="reuseDelay" val="1000" />
		<set name="skillType" val="PDAM" />
		<set name="targetType" val="FRONT_AREA" />
	</skill>
	<skill id="5933" levels="1" name="Dark Blade">
		<!-- Confirmed CT2.5 -->
		<!-- Ekimus Skills -->
		<set name="affectLimit" val="5-15" />
		<set name="affectRange" val="300" />
		<set name="castRange" val="900" />
		<set name="effectRange" val="1500" />
		<set name="element" val="3" /> <!-- Earth -->
		<set name="elementPower" val="180" />
		<set name="fanRange" val="0,0,300,160" />
		<set name="hitTime" val="1500" />
		<set name="magicLvl" val="85" />
		<set name="mpConsume" val="1" />
		<set name="offensive" val="true" />
		<set name="operateType" val="A1" />
		<set name="power" val="9279" />
		<set name="reuseDelay" val="1000" />
		<set name="skillType" val="PDAM" />
		<set name="targetType" val="FRONT_AREA" />
	</skill>
	<skill id="5934" levels="1" name="Meet the soul of darkness and fight against it.">
		<set name="abnormalLvl" val="1" />
		<set name="abnormalTime" val="30" />
		<set name="abnormalType" val="armor_earth" />
		<set name="isMagic" val="1" /> <!-- Magic Skill -->
		<set name="operateType" val="A2" />
		<set name="skillType" val="NOTDONE" />
		<set name="targetType" val="NONE" />
	</skill>
	<skill id="5935" levels="1" name="Dark Ring">
		<!-- Confirmed CT2.5 -->
		<!-- Ekimus Skills -->
		<set name="affectLimit" val="5-15" />
		<set name="affectRange" val="300" />
		<set name="castRange" val="900" />
		<set name="effectRange" val="1500" />
		<set name="element" val="5" /> <!-- Dark -->
		<set name="elementPower" val="180" />
		<set name="hitTime" val="1500" />
		<set name="magicLvl" val="85" />
		<set name="mpConsume" val="1" />
		<set name="offensive" val="true" />
		<set name="operateType" val="A1" />
		<set name="power" val="9279" />
		<set name="reuseDelay" val="1000" />
		<set name="skillType" val="PDAM" />
		<set name="targetType" val="AREA" />
	</skill>
	<skill id="5936" levels="1" name="Earth Ring">
		<!-- Confirmed CT2.5 -->
		<!-- Ekimus Skills -->
		<set name="affectLimit" val="5-15" />
		<set name="affectRange" val="300" />
		<set name="castRange" val="900" />
		<set name="effectRange" val="1500" />
		<set name="element" val="3" /> <!-- Earth -->
		<set name="elementPower" val="180" />
		<set name="hitTime" val="1500" />
		<set name="magicLvl" val="85" />
		<set name="mpConsume" val="1" />
		<set name="offensive" val="true" />
		<set name="operateType" val="A1" />
		<set name="power" val="9279" />
		<set name="reuseDelay" val="1000" />
		<set name="skillType" val="PDAM" />
		<set name="targetType" val="AREA" />
	</skill>
	<skill id="5937" levels="1" name="Self Stun">
		<set name="abnormalLvl" val="1" />
		<set name="abnormalTime" val="9" />
		<set name="abnormalType" val="stun" />
		<set name="operateType" val="A2" />
		<set name="skillType" val="NOTDONE" />
		<set name="targetType" val="NONE" />
	</skill>
	<skill id="5938" levels="5" name="Attack Ability Up">
		<set name="abnormalLvl" val="1" />
		<set name="abnormalTime" val="20" />
		<set name="abnormalType" val="pa_up" />
		<set name="operateType" val="A2" />
		<set name="skillType" val="NOTDONE" />
		<set name="targetType" val="NONE" />
	</skill>
	<skill id="5939" levels="5" name="Defense Ability Up">
		<set name="abnormalLvl" val="1" />
		<set name="abnormalTime" val="20" />
		<set name="abnormalType" val="pd_up" />
		<set name="operateType" val="A2" />
		<set name="skillType" val="NOTDONE" />
		<set name="targetType" val="NONE" />
	</skill>
	<skill id="5940" levels="12" name="Energy of Generation">
		<table name="#abnormalLvls"> 3 4 5 6 7 8 9 10 11 12 13 14 </table>
		<set name="abnormalLvl" val="#abnormalLvls" />
		<set name="abnormalTime" val="300" />
		<set name="abnormalType" val="mp_regen_up" />
		<set name="isMagic" val="1" /> <!-- Magic Skill -->
		<set name="operateType" val="A2" />
		<set name="skillType" val="NOTDONE" />
		<set name="targetType" val="NONE" />
	</skill>
	<skill id="5941" levels="1" name="Energy of Erosion">
		<set name="abnormalLvl" val="4" />
		<set name="abnormalTime" val="300" />
		<set name="abnormalType" val="max_hp_down" />
		<set name="isMagic" val="1" /> <!-- Magic Skill -->
		<set name="operateType" val="A2" />
		<set name="skillType" val="NOTDONE" />
		<set name="targetType" val="NONE" />
	</skill>
	<skill id="5942" levels="1" name="Energy of Pollution">
		<set name="abnormalLvl" val="4" />
		<set name="abnormalTime" val="300" />
		<set name="abnormalType" val="heal_effect_down" />
		<set name="isMagic" val="1" /> <!-- Magic Skill -->
		<set name="operateType" val="A2" />
		<set name="skillType" val="NOTDONE" />
		<set name="targetType" val="NONE" />
	</skill>
	<skill id="5943" levels="1" name="Energy of Contamination">
		<set name="abnormalLvl" val="4" />
		<set name="abnormalTime" val="300" />
		<set name="abnormalType" val="mp_cost_up" />
		<set name="isMagic" val="1" /> <!-- Magic Skill -->
		<set name="operateType" val="A2" />
		<set name="skillType" val="NOTDONE" />
		<set name="targetType" val="NONE" />
	</skill>
	<skill id="5944" levels="1" name="Energy of Oblivion">
		<set name="abnormalLvl" val="4" />
		<set name="abnormalTime" val="300" />
		<set name="abnormalType" val="hit_down" />
		<set name="isMagic" val="1" /> <!-- Magic Skill -->
		<set name="operateType" val="A2" />
		<set name="skillType" val="NOTDONE" />
		<set name="targetType" val="NONE" />
	</skill>
	<skill id="5945" levels="1" name="Region2 Rotation5">
		<set name="abnormalLvl" val="3" />
		<set name="abnormalTime" val="300" />
		<set name="abnormalType" val="max_mp_up" />
		<set name="isMagic" val="1" /> <!-- Magic Skill -->
		<set name="operateType" val="A2" />
		<set name="skillType" val="NOTDONE" />
		<set name="targetType" val="NONE" />
	</skill>
	<skill id="5946" levels="1" name="Large Firework">
		<set name="isMagic" val="2" /> <!-- Static Skill -->
		<set name="operateType" val="A1" />
		<set name="reuseDelay" val="3000" />
		<set name="skillType" val="NOTDONE" />
		<set name="targetType" val="NONE" />
	</skill>
	<skill id="5947" levels="1" name="Large Firework">
		<set name="isMagic" val="2" /> <!-- Static Skill -->
		<set name="operateType" val="A1" />
		<set name="reuseDelay" val="3000" />
		<set name="skillType" val="NOTDONE" />
		<set name="targetType" val="NONE" />
	</skill>
	<skill id="5948" levels="1" name="Large Firework">
		<set name="isMagic" val="2" /> <!-- Static Skill -->
		<set name="operateType" val="A1" />
		<set name="reuseDelay" val="3000" />
		<set name="skillType" val="NOTDONE" />
		<set name="targetType" val="NONE" />
	</skill>
	<skill id="5949" levels="1" name="Large Firework">
		<set name="isMagic" val="2" /> <!-- Static Skill -->
		<set name="operateType" val="A1" />
		<set name="reuseDelay" val="3000" />
		<set name="skillType" val="NOTDONE" />
		<set name="targetType" val="NONE" />
	</skill>
	<skill id="5950" levels="1" name="Birthday Cake">
		<!-- Confirmed CT2.5 -->
		<!-- Birthday Skill -->
		<set name="abnormalLvl" val="9" />
		<set name="abnormalTime" val="43200" />
		<set name="abnormalType" val="vp_up" />
		<set name="aggroPoints" val="100" />
		<set name="castRange" val="900" />
		<set name="effectRange" val="1500" />
		<set name="isMagic" val="2" /> <!-- Static Skill -->
		<set name="operateType" val="A2" />
		<set name="reuseDelay" val="1000" />
		<set name="skillType" val="BUFF" />
		<set name="targetType" val="ONE" />
		<for>
			<effect name="Buff" abnormalTime="43200" val="0" abnormalLvl="9" abnormalType="vp_up" abnormalVisualEffect="vitality">
				<sub stat="vitalityConsumeRate" val="10" />
			</effect>
		</for>
	</skill>
	<skill id="5951" levels="1" name="Agathion's Blessing">
		<set name="hitTime" val="3000" />
		<set name="isMagic" val="2" /> <!-- Static Skill -->
		<set name="operateType" val="A1" />
		<set name="skillType" val="NOTDONE" />
		<set name="targetType" val="NONE" />
	</skill>
	<skill id="5952" levels="1" name="Agathion's Blessing">
		<set name="hitTime" val="3000" />
		<set name="isMagic" val="2" /> <!-- Static Skill -->
		<set name="operateType" val="A1" />
		<set name="skillType" val="NOTDONE" />
		<set name="targetType" val="NONE" />
	</skill>
	<skill id="5953" levels="1" name="Agathion's Blessing">
		<set name="hitTime" val="3000" />
		<set name="isMagic" val="2" /> <!-- Static Skill -->
		<set name="operateType" val="A1" />
		<set name="skillType" val="NOTDONE" />
		<set name="targetType" val="NONE" />
	</skill>
	<skill id="5954" levels="1" name="Agathion Cute Trick - Tin Plate Golem">
		<set name="hitTime" val="3000" />
		<set name="isMagic" val="2" /> <!-- Static Skill -->
		<set name="operateType" val="A1" />
		<set name="skillType" val="NOTDONE" />
		<set name="targetType" val="NONE" />
	</skill>
	<skill id="5955" levels="1" name="Agathion Cute Trick - Joy">
		<set name="hitTime" val="3000" />
		<set name="isMagic" val="2" /> <!-- Static Skill -->
		<set name="operateType" val="A1" />
		<set name="targetType" val="SELF" />
		<cond msgId="2292">
			<player agathionId="16056" />
		</cond>
	</skill>
	<skill id="5956" levels="1" name="Agathion Cute Trick - Anger">
		<set name="hitTime" val="3000" />
		<set name="isMagic" val="2" /> <!-- Static Skill -->
		<set name="operateType" val="A1" />
		<set name="targetType" val="SELF" />
		<cond msgId="2292">
			<player agathionId="16058" />
		</cond>
	</skill>
	<skill id="5957" levels="1" name="Agathion Cute Trick - Sorrow">
		<set name="hitTime" val="3000" />
		<set name="isMagic" val="2" /> <!-- Static Skill -->
		<set name="operateType" val="A1" />
		<set name="targetType" val="SELF" />
		<cond msgId="2292">
			<player agathionId="16057" />
		</cond>
	</skill>
	<skill id="5958" levels="1" name="Agathion Cute Trick - Teddy Bear Boy">
		<set name="hitTime" val="3000" />
		<set name="isMagic" val="2" /> <!-- Static Skill -->
		<set name="operateType" val="A1" />
		<set name="targetType" val="SELF" />
		<cond msgId="2292">
			<player agathionId="16059" />
		</cond>
	</skill>
	<skill id="5959" levels="1" name="Agathion Cute Trick - Teddy Bear Girl">
		<set name="hitTime" val="3000" />
		<set name="isMagic" val="2" /> <!-- Static Skill -->
		<set name="operateType" val="A1" />
		<set name="targetType" val="SELF" />
		<cond msgId="2292">
			<player agathionId="16060" />
		</cond>
	</skill>
	<skill id="5960" levels="1" name="Stronghold Reactivate">
		<set name="abnormalLvl" val="2" />
		<set name="abnormalTime" val="5" />
		<set name="abnormalType" val="poison" />
		<set name="lvlBonusRate" val="1" />
		<set name="operateType" val="A2" />
		<set name="basicProperty" val="CON" />
		<set name="skillType" val="NOTDONE" />
		<set name="targetType" val="NONE" />
		<set name="trait" val="POISON" />
	</skill>
	<skill id="5961" levels="1" name="Barrier Thunder Storm">
		<set name="abnormalLvl" val="1" />
		<set name="abnormalTime" val="9" />
		<set name="abnormalType" val="stun" />
		<set name="affectLimit" val="6-12" />
		<set name="hitTime" val="4000" />
		<set name="lvlBonusRate" val="1" />
		<set name="operateType" val="A2" />
		<set name="basicProperty" val="CON" />
		<set name="skillType" val="NOTDONE" />
		<set name="targetType" val="NONE" />
		<set name="trait" val="SHOCK" />
	</skill>
	<skill id="5962" levels="1" name="Air Defense Cannon">
		<set name="hitTime" val="7000" />
		<set name="operateType" val="A1" />
		<set name="skillType" val="NOTDONE" />
		<set name="targetType" val="NONE" />
	</skill>
	<skill id="5963" levels="1" name="Emery Conversion">
		<set name="hitTime" val="1000" />
		<set name="operateType" val="A1" />
		<set name="skillType" val="NOTDONE" />
		<set name="targetType" val="NONE" />
	</skill>
	<skill id="5964" levels="1" name="Fairy Flame">
		<set name="isMagic" val="2" /> <!-- Static Skill -->
		<set name="operateType" val="A1" />
		<set name="skillType" val="NOTDONE" />
		<set name="targetType" val="NONE" />
	</skill>
	<skill id="5965" levels="1" name="Firework">
		<set name="hitTime" val="500" />
		<set name="isMagic" val="2" /> <!-- Static Skill -->
		<set name="operateType" val="A1" />
		<set name="reuseDelay" val="1000" />
		<set name="targetType" val="SELF" />
	</skill>
	<skill id="5966" levels="1" name="Large Firework">
		<set name="isMagic" val="2" /> <!-- Static Skill -->
		<set name="operateType" val="A1" />
		<set name="reuseDelay" val="3000" />
		<set name="skillType" val="NOTDONE" />
		<set name="targetType" val="NONE" />
	</skill>
	<skill id="5967" levels="2" name="Hate Aura">
		<set name="abnormalLvl" val="1" />
		<set name="abnormalTime" val="3" />
		<set name="abnormalType" val="target_lock" />
		<set name="affectLimit" val="10-10" />
		<set name="lvlBonusRate" val="2" />
		<set name="operateType" val="A2" />
		<set name="reuseDelay" val="40000" />
		<set name="basicProperty" val="MEN" />
		<set name="skillType" val="NOTDONE" />
		<set name="staticReuse" val="true" />
		<set name="targetType" val="NONE" />
	</skill>
	<skill id="5968" levels="2" name="Rapid Shot">
		<table name="#abnormalLvls"> 1 2 </table>
		<set name="abnormalLvl" val="#abnormalLvls" />
		<set name="abnormalTime" val="1200" />
		<set name="abnormalType" val="attack_speed_up_bow" />
		<set name="hitTime" val="1500" />
		<set name="operateType" val="A2" />
		<set name="reuseDelay" val="10000" />
		<set name="skillType" val="NOTDONE" />
		<set name="targetType" val="NONE" />
	</skill>
	<skill id="5969" levels="2" name="Punch of Doom">
		<set name="abnormalLvl" val="1" />
		<set name="abnormalTime" val="9" />
		<set name="abnormalType" val="stun" />
		<set name="coolTime" val="440" />
		<set name="hitTime" val="1360" />
		<set name="lvlBonusRate" val="2" />
		<set name="nextActionAttack" val="true" />
		<set name="operateType" val="A3" />
		<set name="overHit" val="true" />
		<set name="reuseDelay" val="120000" />
		<set name="basicProperty" val="CON" />
		<set name="skillType" val="NOTDONE" />
		<set name="targetType" val="NONE" />
	</skill>
	<skill id="5970" levels="1" name="Seduced Knight's Help">
		<set name="castRange" val="40" />
		<set name="effectRange" val="400" />
		<set name="isMagic" val="1" /> <!-- Magic Skill -->
		<set name="hitTime" val="4000" />
		<set name="magicLvl" val="85" />
		<set name="mpConsume" val="14" />
		<set name="operateType" val="A1" />
		<set name="reuseDelay" val="6000" />
		<set name="skillType" val="BUFF" />
		<set name="targetType" val="ONE" />
		<for>
			<effect name="Buff" abnormalTime="1200" val="0" abnormalLvl="1" abnormalType="public_slot">
				<mul stat="maxHp" val="1.2" />
			</effect>
		</for>
	</skill>
	<skill id="5971" levels="1" name="Seduced Ranger's Help">
		<set name="castRange" val="40" />
		<set name="effectRange" val="400" />
		<set name="hitTime" val="4000" />
		<set name="magicLvl" val="85" />
		<set name="mpConsume" val="14" />
		<set name="operateType" val="A1" />
		<set name="reuseDelay" val="6000" />
		<set name="skillType" val="BUFF" />
		<set name="targetType" val="ONE" />
		<for>
			<effect name="Buff" abnormalTime="1200" val="0" abnormalLvl="1" abnormalType="public_slot">
				<mul stat="regHp" val="1.2" />
			</effect>
		</for>
	</skill>
	<skill id="5972" levels="1" name="Seduced Wizard's Help">
		<set name="castRange" val="40" />
		<set name="effectRange" val="400" />
		<set name="hitTime" val="4000" />
		<set name="magicLvl" val="85" />
		<set name="mpConsume" val="14" />
		<set name="operateType" val="A1" />
		<set name="reuseDelay" val="6000" />
		<set name="skillType" val="BUFF" />
		<set name="targetType" val="ONE" />
		<for>
			<effect name="Buff" abnormalTime="1200" val="0" abnormalLvl="1" abnormalType="public_slot">
				<mul stat="maxMp" val="1.2" />
			</effect>
		</for>
	</skill>
	<skill id="5973" levels="1" name="Seduced Warrior's Help">
		<set name="castRange" val="40" />
		<set name="effectRange" val="400" />
		<set name="hitTime" val="4000" />
		<set name="magicLvl" val="85" />
		<set name="mpConsume" val="14" />
		<set name="operateType" val="A1" />
		<set name="reuseDelay" val="6000" />
		<set name="skillType" val="BUFF" />
		<set name="targetType" val="ONE" />
		<for>
			<effect name="Buff" abnormalTime="1200" val="0" abnormalLvl="1" abnormalType="public_slot">
				<mul stat="regMp" val="1.2" />
			</effect>
		</for>
	</skill>
	<skill id="5974" levels="1" name="Tiat Transformation">
		<set name="abnormalLvl" val="1" />
		<set name="abnormalTime" val="7800" />
		<set name="abnormalType" val="transform" />
		<set name="hitTime" val="7900" />
		<set name="operateType" val="A2" />
		<set name="reuseDelay" val="1000" />
		<set name="skillType" val="NOTDONE" />
		<set name="targetType" val="NONE" />
	</skill>
	<skill id="5975" levels="3" name="Dark Attack">
		<table name="#magicLvl"> 51 61 79 </table>
		<table name="#mpConsume"> 50 61 75 </table>
		<table name="#power"> 1515 2365 6059 </table>
		<set name="castRange" val="40" />
		<set name="effectRange" val="400" />
		<set name="hitTime" val="1000" />
		<set name="magicLvl" val="#magicLvl" />
		<set name="mpConsume" val="#mpConsume" />
		<set name="offensive" val="true" />
		<set name="operateType" val="A1" />
		<set name="power" val="#power" />
		<set name="reuseDelay" val="1000" />
		<set name="skillType" val="PDAM" />
		<set name="targetType" val="ONE" />
	</skill>
	<skill id="5976" levels="3" name="Dark Storm">
		<table name="#magicLvl"> 51 61 79 </table>
		<table name="#mpConsume"> 50 61 75 </table>
		<table name="#power"> 757 1182 4039 </table>
		<set name="affectLimit" val="10-10" />
		<set name="affectRange" val="100" />
		<set name="hitTime" val="2500" />
		<set name="magicLvl" val="#magicLvl" />
		<set name="mpConsume" val="#mpConsume" />
		<set name="offensive" val="true" />
		<set name="operateType" val="A1" />
		<set name="power" val="#power" />
		<set name="reuseDelay" val="1000" />
		<set name="skillType" val="PDAM" />
		<set name="targetType" val="AURA" />
	</skill>
	<skill id="5977" levels="3" name="Dark Strike">
		<set name="hitTime" val="1000" />
		<set name="operateType" val="A1" />
		<set name="reuseDelay" val="1000" />
		<set name="skillType" val="NOTDONE" />
		<set name="targetType" val="NONE" />
	</skill>
	<skill id="5978" levels="1" name="Death Strike">
		<set name="hitTime" val="1500" />
		<set name="operateType" val="A1" />
		<set name="reuseDelay" val="1000" />
		<set name="castRange" val="500" />
		<set name="targetType" val="ONE" />
	</skill>
	<skill id="5979" levels="1" name="Forced Move">
		<set name="hitTime" val="2500" />
		<set name="operateType" val="A1" />
		<set name="reuseDelay" val="2000" />
		<set name="skillType" val="NOTDONE" />
		<set name="targetType" val="NONE" />
	</skill>
	<skill id="5980" levels="3" name="Seal Isolation">
		<set name="affectLimit" val="10-10" />
		<set name="affectRange" val="300" />
		<set name="hitTime" val="2500" />
		<set name="power" val="200"/>
		<set name="mpConsume" val="50" />
		<set name="operateType" val="A1" />
		<set name="reuseDelay" val="1000"/>
		<set name="skillType" val="MDAM"/>
		<set name="targetType" val="AURA" />
		<for>
			<effect name="RemoveTarget" noicon="1" val="0">
				<param chance="50" />
			</effect>
		</for>
	</skill>
	<skill id="5981" levels="3" name="Lilith's Curse">
		<set name="abnormalLvl" val="3" />
		<set name="abnormalTime" val="300" />
		<set name="abnormalType" val="speed_down" />
		<set name="isMagic" val="1" /> <!-- Magic Skill -->
		<set name="operateType" val="A2" />
		<set name="skillType" val="NOTDONE" />
		<set name="targetType" val="NONE" />
	</skill>
	<skill id="5982" levels="1" name="Aura Bird - Falcon">
		<set name="abnormalLvl" val="1" />
		<set name="abnormalTime" val="-1" />
		<set name="abnormalType" val="transform" />
		<set name="castRange" val="1500" />
		<set name="effectRange" val="2100" />
		<set name="hitTime" val="2500" />
		<set name="isMagic" val="2" /> <!-- Static Skill -->
		<set name="magicLvl" val="75" />
		<set name="mpConsume" val="75" />
		<set name="operateType" val="A2" />
		<set name="reuseDelay" val="7200000" />
		<set name="skillType" val="CONT" />
		<set name="targetType" val="ONE" />
		<set name="transformId" val="8" />
		<cond msgId="2721">
			<player landingZone="true" />
		</cond>
		<cond>
			<player canTransform="true" />
		</cond>
		<for>
			<effect name="Transformation" abnormalTime="-1" val="0" abnormalLvl="1" abnormalType="transform"> <!-- Transformation has unlimited time -->
				<mul stat="reduceExpLostByPvp" val="0.1" />
				<mul stat="reduceExpLostByMob" val="0.1" />
				<mul stat="reduceExpLostByRaid" val="0.1" />
			</effect>
		</for>
	</skill>
	<skill id="5983" levels="1" name="Aura Bird - Owl">
		<set name="abnormalLvl" val="1" />
		<set name="abnormalTime" val="-1" />
		<set name="abnormalType" val="transform" />
		<set name="castRange" val="1500" />
		<set name="effectRange" val="2100" />
		<set name="hitTime" val="2500" />
		<set name="isMagic" val="2" /> <!-- Static Skill -->
		<set name="magicLvl" val="75" />
		<set name="mpConsume" val="75" />
		<set name="operateType" val="A2" />
		<set name="reuseDelay" val="7200000" />
		<set name="skillType" val="CONT" />
		<set name="targetType" val="ONE" />
		<set name="transformId" val="9" />
		<cond msgId="2721">
			<player landingZone="true" />
		</cond>
		<cond>
			<player canTransform="true" />
		</cond>
		<for>
			<effect name="Transformation" abnormalTime="-1" val="0" abnormalLvl="1" abnormalType="transform"> <!-- Transformation has unlimited time -->
				<mul stat="reduceExpLostByPvp" val="0.1" />
				<mul stat="reduceExpLostByMob" val="0.1" />
				<mul stat="reduceExpLostByRaid" val="0.1" />
			</effect>
		</for>
	</skill>
	<skill id="5984" levels="1" name="Hand of Death">
		<set name="abnormalLvl" val="1" />
		<set name="abnormalTime" val="60" />
		<set name="abnormalType" val="md_down" />
		<set name="lvlBonusRate" val="1" />
		<set name="operateType" val="A2" />
		<set name="basicProperty" val="MEN" />
		<set name="skillType" val="NOTDONE" />
		<set name="targetType" val="NONE" />
	</skill>
	<skill id="5985" levels="9" name="Decaying Aura">
		<table name="#abnormalLvls"> 1 2 3 4 5 6 7 8 9 </table>
		<set name="abnormalLvl" val="#abnormalLvls" />
		<set name="abnormalTime" val="3600" />
		<set name="abnormalType" val="dmg_shield" />
		<set name="isMagic" val="1" /> <!-- Magic Skill -->
		<set name="operateType" val="A2" />
		<set name="skillType" val="NOTDONE" />
		<set name="targetType" val="NONE" />
	</skill>
	<skill id="5986" levels="9" name="Vampiric Aura">
		<table name="#abnormalLvls"> 1 2 3 4 5 6 7 8 9 </table>
		<set name="abnormalLvl" val="#abnormalLvls" />
		<set name="abnormalTime" val="3600" />
		<set name="abnormalType" val="vampiric_attack" />
		<set name="isMagic" val="1" /> <!-- Magic Skill -->
		<set name="operateType" val="A2" />
		<set name="skillType" val="NOTDONE" />
		<set name="targetType" val="NONE" />
	</skill>
	<skill id="5987" levels="1" name="Weapon Maintenance">
		<!-- Confirmed CT2.5 -->
		<set name="abnormalLvl" val="1" />
		<set name="abnormalTime" val="600" />
		<set name="abnormalType" val="dwarf_attack_buff" />
		<set name="affectRange" val="300" />
		<set name="aggroPoints" val="467" />
		<set name="coolTime" val="500" />
		<set name="hitTime" val="1000" />
		<set name="magicLvl" val="85" />
		<set name="mpConsume" val="41" />
		<set name="operateType" val="A2" />
		<set name="reuseDelay" val="6000" />
		<set name="skillType" val="BUFF" />
		<set name="targetType" val="PARTY" />
		<for>
			<effect name="Buff" abnormalTime="600" val="0" abnormalLvl="1" abnormalType="dwarf_attack_buff">
				<mul stat="pAtk" val="1.05">
					<using kind="SWORD,DAGGER,DUALDAGGER,POLE,RAPIER,ANCIENTSWORD,DUAL,DUALFIST,BLUNT,BOW,CROSSBOW" />
				</mul>
				<basemul stat="critRate" val="0.2">
					<using kind="SWORD,DAGGER,DUALDAGGER,POLE,RAPIER,ANCIENTSWORD,DUAL,DUALFIST" />
				</basemul>
				<add stat="pAtkRange" val="100">
					<using kind="BOW,CROSSBOW" />
				</add>
				<add stat="stunProf" val="8" />
			</effect>
		</for>
	</skill>
	<skill id="5988" levels="1" name="Armor Maintenance">
		<!-- Confirmed CT2.5 -->
		<set name="abnormalLvl" val="1" />
		<set name="abnormalTime" val="600" />
		<set name="abnormalType" val="dwarf_defence_buff" />
		<set name="affectRange" val="300" />
		<set name="aggroPoints" val="438" />
		<set name="coolTime" val="500" />
		<set name="hitTime" val="1000" />
		<set name="magicLvl" val="85" />
		<set name="mpConsume" val="41" />
		<set name="operateType" val="A2" />
		<set name="reuseDelay" val="6000" />
		<set name="skillType" val="BUFF" />
		<set name="targetType" val="PARTY" />
		<for>
			<effect name="Buff" abnormalTime="600" val="0" abnormalLvl="1" abnormalType="dwarf_defence_buff">
				<mul stat="pDef" val="1.1">
					<using kind="HEAVY" />
				</mul>
				<mul stat="pDef" val="1.05">
					<using kind="LIGHT" />
				</mul>
				<add stat="rEvas" val="2">
					<using kind="LIGHT" />
				</add>
				<mul stat="pDef" val="1.05">
					<using kind="MAGIC" />
				</mul>
				<add stat="regMp" val="2.0">
					<using kind="MAGIC" />
				</add>
			</effect>
		</for>
	</skill>
	<skill id="5989" levels="1" name="Invincible">
		<set name="abnormalLvl" val="1" />
		<set name="abnormalTime" val="60" />
		<set name="abnormalType" val="invincibility" />
		<set name="hitTime" val="3500" />
		<set name="operateType" val="A2" />
		<set name="reuseDelay" val="6000" />
		<set name="skillType" val="NOTDONE" />
		<set name="targetType" val="NONE" />
	</skill>
	<skill id="5990" levels="3" name="Lesser Heal">
		<set name="hitTime" val="2000" />
		<set name="isMagic" val="1" /> <!-- Magic Skill -->
		<set name="operateType" val="A1" />
		<set name="reuseDelay" val="3000" />
		<set name="skillType" val="NOTDONE" />
		<set name="targetType" val="NONE" />
	</skill>
	<skill id="5991" levels="1" name="Presentation - Summon Tiat">
		<set name="hitTime" val="11760" />
		<set name="isMagic" val="2" /> <!-- Static Skill -->
		<set name="operateType" val="A1" />
		<set name="skillType" val="NOTDONE" />
		<set name="targetType" val="NONE" />
	</skill>
	<skill id="5992" levels="12" name="NPC Hate">
		<set name="abnormalLvl" val="1" />
		<set name="abnormalTime" val="3" />
		<set name="abnormalType" val="target_lock" />
		<set name="lvlBonusRate" val="2" />
		<set name="operateType" val="A2" />
		<set name="basicProperty" val="MEN" />
		<set name="skillType" val="NOTDONE" />
		<set name="targetType" val="NONE" />
	</skill>
	<skill id="5993" levels="1" name="Command of Anger">
		<!-- Confirmed CT2.5 -->
		<!-- Ekimus Skills -->
		<set name="abnormalLvl" val="8" />
		<set name="abnormalTime" val="10" />
		<set name="abnormalType" val="oblivion" />
		<set name="affectLimit" val="10-10" />
		<set name="affectRange" val="300" />
		<set name="hitTime" val="2000" />
		<set name="isMagic" val="1" /> <!-- Magic Skill -->
		<set name="lvlBonusRate" val="1" />
		<set name="magicLvl" val="85" />
		<set name="mpConsume" val="60" />
		<set name="mpInitialConsume" val="15" />
		<set name="offensive" val="true" />
		<set name="operateType" val="A2" />
		<set name="power" val="171" />
		<set name="basicProperty" val="MEN" />
		<set name="skillType" val="MDAM" />
		<set name="targetType" val="AURA" />
		<set name="trait" val="DERANGEMENT" />
		<for>
			<effect name="TriggerSkillByDamage" abnormalTime="10" val="0" abnormalVisualEffect="poison" effectPower="90" abnormalLvl="8" abnormalType="oblivion">
				<param attackerType="L2Attackable" minAttackerLevel="1" maxAttackerLevel="100" />
				<param minDamage="1" />
				<param chance="90" />
				<param skillId="5902" skillLevel="1" /> <!-- NPC Trigger Target Cancel -->
				<param targetType="SELF" />
			</effect>
			<effect name="Mute" abnormalTime="10" noicon="1" val="0" effectPower="90" />
			<effect name="PhysicalMute" abnormalTime="10" noicon="1" val="0" effectPower="90" />
		</for>
	</skill>
	<skill id="5994" levels="1" name="Effect of Doubt">
		<set name="abnormalLvl" val="1" />
		<set name="abnormalTime" val="1800" />
		<set name="abnormalType" val="big_head" />
		<set name="castRange" val="900" />
		<set name="effectRange" val="1400" />
		<set name="isDebuff" val="true" />
		<set name="isMagic" val="2" /> <!-- Static Skill -->
		<set name="operateType" val="A2" />
		<set name="power" val="-1" /> <!-- Land Always -->
		<set name="offensive" val="true" />
		<set name="skillType" val="DEBUFF" />
		<set name="targetType" val="ONE" />
		<set name="trait" val="ETC" />
		<for>
			<effect name="BigHead" abnormalTime="1800" val="0" abnormalVisualEffect="bighead" abnormalLvl="1" abnormalType="big_head" />
		</for>
	</skill>
	<skill id="5995" levels="1" name="not_used">
		<set name="operateType" val="P" />
		<set name="skillType" val="NOTDONE" />
		<set name="targetType" val="NONE" />
	</skill>
	<skill id="5996" levels="1" name="not_used">
		<set name="operateType" val="P" />
		<set name="skillType" val="NOTDONE" />
		<set name="targetType" val="NONE" />
	</skill>
	<skill id="5997" levels="1" name="not_used">
		<set name="operateType" val="P" />
		<set name="skillType" val="NOTDONE" />
		<set name="targetType" val="NONE" />
	</skill>
	<skill id="5998" levels="1" name="not_used">
		<set name="operateType" val="P" />
		<set name="skillType" val="NOTDONE" />
		<set name="targetType" val="NONE" />
	</skill>
	<skill id="5999" levels="1" name="not_used">
		<set name="operateType" val="P" />
		<set name="skillType" val="NOTDONE" />
		<set name="targetType" val="NONE" />
	</skill>
</list>
